LICENSE
MANIFEST.in
README.md
requirements.txt
setup.py
RPD.egg-info/PKG-INFO
RPD.egg-info/SOURCES.txt
RPD.egg-info/dependency_links.txt
RPD.egg-info/requires.txt
RPD.egg-info/top_level.txt
rpd/__init__.py
rpd/__main__.py
rpd/banner.txt
rpd/color.py
rpd/colour.py
rpd/file.py
rpd/flags.py
rpd/intents.py
rpd/py.typed
rpd/snowflake.py
rpd/state.py
rpd/traits.py
rpd/ui.py
rpd/webhooks.py
rpd/api/__init__.py
rpd/api/gateway.py
rpd/api/rest.py
rpd/api/rest_factory.py
rpd/apps/__init__.py
rpd/apps/bot.py
rpd/apps/webhooks.py
rpd/audio/__init__.py
rpd/audio/client.py
rpd/audio/ffmpeg.py
rpd/audio/gateway.py
rpd/audio/opus.py
rpd/cache/__init__.py
rpd/cache/cdn.py
rpd/cache/embed.py
rpd/cache/guild.py
rpd/cache/message.py
rpd/cache/user.py
rpd/components/__init__.py
rpd/components/core.py
rpd/events/__init__.py
rpd/events/core.py
rpd/events/messages.py
rpd/events/voice.py
rpd/implements/__init__.py
rpd/implements/core.py
rpd/interactions/__init__.py
rpd/interactions/chat_input.py
rpd/interactions/command.py
rpd/interactions/option.py
rpd/internal/__init__.py
rpd/internal/dispatcher.py
rpd/internal/exceptions.py
rpd/internal/warnings.py
rpd/modules/__init__.py
rpd/modules/core.py
rpd/types/__init__.py
rpd/types/allowed_mentions.py
rpd/util/__init__.py
rpd/util/ciso_parse.py
rpd/util/missing.py