Metadata-Version: 2.1
Name: RPD
Version: 0.6.0
Summary: Asynchronous Discord API Wrapper For Python
Home-page: https://github.com/RPD-py/RPD
Author: VincentRPS
License: MIT
Project-URL: Documentation, https://RPD.rtfd.io
Project-URL: Issue Tracker, https://github.com/RPD-py/RPD/issues
Project-URL: Pull Request Tracker, https://github.com/RPD-py/RPD/pulls
Platform: UNKNOWN
Classifier: Development Status :: 4 - Beta
Classifier: License :: OSI Approved :: MIT License
Classifier: Intended Audience :: Developers
Classifier: Natural Language :: English
Classifier: Operating System :: OS Independent
Classifier: Programming Language :: Python :: 3.8
Classifier: Programming Language :: Python :: 3.9
Classifier: Programming Language :: Python :: 3.10
Classifier: Programming Language :: Python :: Implementation :: CPython
Classifier: Framework :: AsyncIO
Classifier: Framework :: aiohttp
Classifier: Topic :: Communications :: Chat
Classifier: Topic :: Internet :: WWW/HTTP
Classifier: Topic :: Internet
Classifier: Topic :: Software Development :: Libraries
Classifier: Topic :: Software Development :: Libraries :: Python Modules
Classifier: Topic :: Utilities
Requires-Python: >=3.8
Provides-Extra: speed
Provides-Extra: audio
License-File: LICENSE
